<biblStruct   xml:id="b0">
	<monogr>
		<title level="m" type="main">Mujo deluks</title>
		<imprint>
			<date type="published" when="1972" />
		</imprint>
	</monogr>
</biblStruct>

<biblStruct   xml:id="b1">
	<analytic>
		<title level="a" type="main">Jugosloveni hrane Nemce</title>
	</analytic>
	<monogr>
		<title level="m">Ekspres politika, 13.05</title>
		<imprint>
			<date type="published" when="1973" />
		</imprint>
	</monogr>
</biblStruct>

<biblStruct   xml:id="b2">
	<analytic>
		<title level="a" type="main">Ustav SFRJ 1974</title>
	</analytic>
	<monogr>
		<title level="j">In: Službeni list SFRJ</title>
		<imprint>
			<biblScope unit="volume">3074</biblScope>
			<biblScope unit="issue">9</biblScope>
			<date type="published" when="1974" />
		</imprint>
	</monogr>
</biblStruct>

<biblStruct   xml:id="b3">
	<analytic>
		<title/>
	</analytic>
	<monogr>
		<title level="j">Ustav SFRJ. In: Službeni list</title>
		<imprint>
			<biblScope unit="volume">1977</biblScope>
			<date type="published" when="1977" />
		</imprint>
	</monogr>
</biblStruct>

<biblStruct   xml:id="b4">
	<monogr>
		<title level="m" type="main">Zwanglos und ganz ohne Programm</title>
		<imprint>
			<date type="published" when="1977" />
			<publisher>Mannheimer Morgen</publisher>
			<biblScope unit="page" from="1" to="12" />
		</imprint>
	</monogr>
</biblStruct>

<biblStruct   xml:id="b5">
	<analytic>
		<title level="a" type="main">Ne možemo svi u kafedžije</title>
	</analytic>
	<monogr>
		<title level="m">Ilustrovana Politika, 22.03</title>
		<imprint>
			<date type="published" when="1978" />
		</imprint>
	</monogr>
</biblStruct>

<biblStruct   xml:id="b6">
	<monogr>
		<title level="m" type="main">Vom Čimbur bis Gibanica. Rezepte aus Jugoslawien</title>
		<imprint>
			<date type="published" when="1987" />
			<publisher>Verlag für die Frau</publisher>
			<pubPlace>Leipzig</pubPlace>
		</imprint>
	</monogr>
</biblStruct>

<biblStruct   xml:id="b7">
	<monogr>
		<title level="m" type="main">Jugoslawische Restaurants Online verfügbar unter</title>
		<imprint/>
	</monogr>
</biblStruct>

<biblStruct   xml:id="b8">
	<monogr>
		<title level="m" type="main">Generalni konzulat Minhen SSIP-u, 01.11</title>
		<imprint>
			<date type="published" when="1975" />
			<pubPlace>DASMIP, PA</pubPlace>
		</imprint>
	</monogr>
</biblStruct>

<biblStruct   xml:id="b9">
	<monogr>
		<title level="m" type="main">Imagination und Identität. Psychosoziale Aspekte und kulturübergreifende Therapie</title>
		<author>
			<persName>
				<forename type="first">Salman</forename>
				<surname>Ahtakar</surname>
			</persName>
		</author>
		<imprint>
			<date type="published" when="2007" />
			<publisher>Psychosozial-Verlag</publisher>
			<pubPlace>Gießen</pubPlace>
		</imprint>
	</monogr>
</biblStruct>

<biblStruct   xml:id="b10">
	<analytic>
		<title level="a" type="main">How to make a National Cuisine: Cookbooks in Contemporary India</title>
		<author>
			<persName>
				<forename type="first">Arjun</forename>
				<surname>Appadurai</surname>
			</persName>
		</author>
	</analytic>
	<monogr>
		<title level="j">In: Comparative Studies in Society and History</title>
		<imprint>
			<biblScope unit="volume">30</biblScope>
			<biblScope unit="issue">1</biblScope>
			<biblScope unit="page" from="3" to="24" />
			<date type="published" when="1988" />
		</imprint>
	</monogr>
</biblStruct>

<biblStruct   xml:id="b11">
	<monogr>
		<title level="m" type="main">Was sind Repräsentationen sozialer Ordnungen im Wandel? Anmerkungen zu einer Geschichte interkultureller Begegnungen In: Jörg Baberowski (Hg.): Arbeit an der Geschichte. Wie viel Theorie braucht die Geschichtswissenschaft? Frankfurt am Main</title>
		<author>
			<persName>
				<forename type="first">Jörg</forename>
				<surname>Baberowski</surname>
			</persName>
		</author>
		<imprint>
			<date type="published" when="2009" />
			<biblScope unit="page" from="7" to="18" />
			<pubPlace>New York: Campus, S</pubPlace>
		</imprint>
	</monogr>
</biblStruct>

<biblStruct   xml:id="b12">
	<monogr>
		<title level="m" type="main">Immigration, incorporation &amp; transnationalism</title>
		<author>
			<persName>
				<forename type="first">Elliott</forename>
				<surname>Barkan</surname>
			</persName>
		</author>
		<author>
			<persName>
				<surname>Robert</surname>
			</persName>
		</author>
		<imprint>
			<date type="published" when="2007" />
			<publisher>Transaction Publishers</publisher>
			<pubPlace>New Brunswick</pubPlace>
		</imprint>
	</monogr>
</biblStruct>

<biblStruct   xml:id="b13">
	<analytic>
		<title level="a" type="main">Rückkehr und Reintegration jugoslawischer Arbeitnehmer aus der Bundesrepublik Deutschland</title>
		<author>
			<persName>
				<forename type="first">Ivo</forename>
				<surname>Baučić</surname>
			</persName>
		</author>
		<author>
			<persName>
				<forename type="first">Bernd</forename>
				<surname>Groß</surname>
			</persName>
		</author>
	</analytic>
	<monogr>
		<title level="j">Bonn: Bundesministerium für Arbeit und Soziales</title>
		<imprint>
			<publisher>Forschungsbericht Sozialforschung</publisher>
			<biblScope unit="volume">163</biblScope>
			<biblScope unit="issue">9</biblScope>
			<date type="published" when="1988" />
			<publisher>Forschungsbericht Sozialforschung</publisher>
		</imprint>
	</monogr>
</biblStruct>

<biblStruct   xml:id="b14">
	<analytic>
		<title level="a" type="main">Food nations. Selling taste in consumer societies</title>
		<author>
			<persName>
				<forename type="first">Warren</forename>
				<surname>Belasco</surname>
			</persName>
		</author>
		<author>
			<persName>
				<surname>James</surname>
			</persName>
		</author>
	</analytic>
	<monogr>
		<title level="j">Routledge</title>
		<imprint>
			<date type="published" when="2002" />
		</imprint>
	</monogr>
	<note>Hagley. perspectives on business and culture</note>
</biblStruct>

<biblStruct   xml:id="b15">
	<monogr>
		<title level="m" type="main">Eating up Yugoslavia, Cookbooks and Consumption in Socialist Yugoslavia Communism Unwrappred: Consumption in Cold War Eastern Europe. Oxford</title>
		<author>
			<persName>
				<forename type="first">Wendy</forename>
				<surname>Bracewell</surname>
			</persName>
		</author>
		<editor>Paulina Bren und Mary Neuburger (Hg</editor>
		<imprint>
			<date type="published" when="2012" />
			<publisher>Oxford University Press</publisher>
			<biblScope unit="page" from="169" to="196" />
			<pubPlace>New York</pubPlace>
		</imprint>
	</monogr>
</biblStruct>

<biblStruct   xml:id="b16">
	<monogr>
		<title/>
		<author>
			<persName>
				<forename type="first">Gunilla-Friederike ;</forename>
				<surname>Budde</surname>
			</persName>
		</author>
		<author>
			<persName>
				<surname>Conrad</surname>
			</persName>
		</author>
		<author>
			<persName>
				<surname>Sebastian</surname>
			</persName>
		</author>
		<author>
			<persName>
				<forename type="first">Oliver</forename>
				<surname>Janz</surname>
			</persName>
		</author>
		<imprint>
			<date type="published" when="2006" />
			<publisher>Transnationale Geschichte. Themen, Tendenzen und Theorien Vandenhoeck &amp; Ruprecht</publisher>
			<pubPlace>Göttingen</pubPlace>
		</imprint>
	</monogr>
</biblStruct>

<biblStruct   xml:id="b17">
	<monogr>
		<title level="m" type="main">Geschichte Jugoslawiens im 20</title>
		<author>
			<persName>
				<forename type="first">Marie-Janine</forename>
				<surname>Calic</surname>
			</persName>
		</author>
		<imprint>
			<date type="published" when="2010" />
		</imprint>
	</monogr>
</biblStruct>

<biblStruct   xml:id="b18">
	<analytic>
		<title level="a" type="main">Dynamik der Beziehungen der Migranten zum Herkunftsland: biographische Perspektive</title>
		<author>
			<persName>
				<forename type="first">Čapo</forename>
				<surname>Žmegač</surname>
			</persName>
		</author>
		<author>
			<persName>
				<forename type="first">Jasna</forename>
			</persName>
		</author>
	</analytic>
	<monogr>
		<title level="m">Schweizerisches Archiv für Volkskunde 102</title>
		<imprint>
			<date type="published" when="2006" />
			<biblScope unit="page" from="1" to="20" />
		</imprint>
	</monogr>
</biblStruct>

<biblStruct   xml:id="b19">
	<analytic>
		<title level="a" type="main">O povratku naših radnika iz inostranstva</title>
		<author>
			<persName>
				<forename type="first">Milena</forename>
				<surname>Davidović-Primorac</surname>
			</persName>
		</author>
	</analytic>
	<monogr>
		<title level="j">In: Sociološki pregled</title>
		<imprint>
			<biblScope unit="volume">16</biblScope>
			<biblScope unit="issue">12</biblScope>
			<biblScope unit="page" from="5" to="45" />
			<date type="published" when="1982" />
		</imprint>
	</monogr>
</biblStruct>

<biblStruct   xml:id="b20">
	<analytic>
		<title level="a" type="main">Balkan-Küche. Über 150 Rezepte: von pfefferscharf bis zuckersüß</title>
		<author>
			<persName>
				<forename type="first">Renate</forename>
				<surname>Derndinger</surname>
			</persName>
		</author>
	</analytic>
	<monogr>
		<title level="m">Herrsching: Pawlak (Burda)</title>
		<imprint>
			<date type="published" when="1989" />
		</imprint>
	</monogr>
</biblStruct>

<biblStruct   xml:id="b21">
	<monogr>
		<title level="m" type="main">Inventing Ruritania, Imperialism of Imagination</title>
		<author>
			<persName>
				<forename type="first">Vesna</forename>
				<surname>Goldsworthy</surname>
			</persName>
		</author>
		<imprint>
			<date type="published" when="1998" />
			<publisher>Yale University Press</publisher>
			<pubPlace>New Haven</pubPlace>
		</imprint>
	</monogr>
</biblStruct>

<biblStruct   xml:id="b22">
	<monogr>
		<title level="m" type="main">The Ambiguous Nation. Socialist and Post-Socialist NationBuilding in Southeastern Europe in Perspective (Introduction) In: Ulf Brunnbauer und Hannes Grandits (Hg.): The Ambiguous Nation. Case Studies from Southeastern Europe in the 20th Century</title>
		<author>
			<persName>
				<forename type="first">Hannes</forename>
				<surname>Grandits</surname>
			</persName>
		</author>
		<author>
			<persName>
				<forename type="first">Ulf</forename>
				<surname>Brunnbauer</surname>
			</persName>
		</author>
		<imprint>
			<date type="published" when="2013" />
			<publisher>Oldenbourg Verlag (Südosteuropäische Arbeiten</publisher>
			<biblScope unit="page" from="151" to="160" />
			<pubPlace>München</pubPlace>
		</imprint>
	</monogr>
</biblStruct>

<biblStruct   xml:id="b23">
	<monogr>
		<title level="m" type="main">How food made history</title>
		<author>
			<persName>
				<forename type="first">Barry</forename>
				<forename type="middle">W</forename>
				<surname>Higman</surname>
			</persName>
		</author>
		<imprint>
			<date type="published" when="2012" />
			<publisher>Wiley-Blackwell</publisher>
			<pubPlace>Malden</pubPlace>
		</imprint>
	</monogr>
</biblStruct>

<biblStruct   xml:id="b24">
	<monogr>
		<title level="m" type="main">The Invention of Tradition</title>
		<author>
			<persName>
				<forename type="first">Eric</forename>
				<surname>Hobsbawm</surname>
			</persName>
		</author>
		<imprint>
			<date type="published" when="1992" />
			<publisher>Cambridge University Press</publisher>
			<pubPlace>Cambridge</pubPlace>
		</imprint>
	</monogr>
</biblStruct>

<biblStruct   xml:id="b25">
	<monogr>
		<title level="m" type="main">Age of extremes. The short twentieth century</title>
		<author>
			<persName>
				<forename type="first">Eric</forename>
				<forename type="middle">J</forename>
				<surname>Hobsbawm</surname>
			</persName>
		</author>
		<imprint>
			<date type="published" when="1914" />
			<publisher>Michael Joseph</publisher>
			<pubPlace>London</pubPlace>
		</imprint>
	</monogr>
</biblStruct>

<biblStruct   xml:id="b26">
	<monogr>
		<title level="m" type="main">Interview mit dem Besitzer des Imbiss Restaurants „Balkan grill“. Berlin, 14.04</title>
		<imprint>
			<date type="published" when="2013" />
		</imprint>
	</monogr>
</biblStruct>

<biblStruct   xml:id="b27">
	<monogr>
		<title level="m" type="main">Interview mit dem Besitzer des Restaurants „Adriatic“. Berlin, 30.04</title>
		<imprint>
			<date type="published" when="2013" />
		</imprint>
	</monogr>
</biblStruct>

<biblStruct   xml:id="b28">
	<monogr>
		<title level="m" type="main">Interview mit dem Besitzer des Restaurants „Dalmacija Grill“, Potsdamer Straße</title>
		<imprint>
			<biblScope unit="page" from="27" to="31" />
			<pubPlace>Berlin</pubPlace>
		</imprint>
	</monogr>
</biblStruct>

<biblStruct   xml:id="b29">
	<monogr>
		<title level="m" type="main">Interview mit dem Besitzer des Restaurants „Dalmacija grill“. Berlin, 27.04</title>
		<imprint>
			<date type="published" when="2013" />
		</imprint>
	</monogr>
</biblStruct>

<biblStruct   xml:id="b30">
	<analytic>
		<title/>
	</analytic>
	<monogr>
		<title level="j">Interview mit dem Besitzer des Restaurants „Emona“</title>
		<imprint>
			<date type="published" when="2013" />
		</imprint>
	</monogr>
</biblStruct>

<biblStruct   xml:id="b31">
	<analytic>
		<title/>
	</analytic>
	<monogr>
		<title level="j">Interview mit dem Besitzer des Restaurants „Marko Schlemmerstube“. Berlin</title>
		<imprint>
			<biblScope unit="page" from="29" to="33" />
		</imprint>
	</monogr>
</biblStruct>

<biblStruct   xml:id="b32">
	<monogr>
		<title level="m" type="main">Interview mit dem Besitzer des Restaurants „Split“ und mit dem Besitzer des Restaurants „Dalmacija“</title>
		<imprint/>
	</monogr>
</biblStruct>

<biblStruct   xml:id="b33">
	<monogr>
		<title level="m" type="main">Interview mit dem Besitzer des Restaurants „Split“. Berlin, 22.04</title>
		<imprint>
			<date type="published" when="2013" />
		</imprint>
	</monogr>
</biblStruct>

<biblStruct   xml:id="b34">
	<monogr>
		<title level="m" type="main">Interview mit dem Besitzer des Restaurants „Tijarica“. Split, 22.08</title>
		<imprint>
			<date type="published" when="2013" />
		</imprint>
	</monogr>
</biblStruct>

<biblStruct   xml:id="b35">
	<monogr>
		<title level="m" type="main">Interview mit dem Besitzer des Restaurants „Ziko grill“. Berlin, 29.04</title>
		<imprint>
			<date type="published" when="2013" />
		</imprint>
	</monogr>
</biblStruct>

<biblStruct   xml:id="b36">
	<monogr>
		<title level="m" type="main">Geburtstag pišeš normalno Jugoslovenski gastarbajteri u Austriji i SR Nemačkoj (1965-1973)</title>
		<author>
			<persName>
				<forename type="first">Vladimir</forename>
				<surname>Ivanović</surname>
			</persName>
		</author>
		<imprint>
			<date type="published" when="2012" />
			<pubPlace>Beograd</pubPlace>
		</imprint>
	</monogr>
	<note>Institut. za savremenu istoriju</note>
</biblStruct>

<biblStruct   xml:id="b37">
	<monogr>
		<title/>
		<author>
			<persName>
				<forename type="first">Stevo</forename>
				<surname>Karapandža</surname>
			</persName>
		</author>
		<author>
			<persName>
				<forename type="first">Janez</forename>
				<surname>Bogataj</surname>
			</persName>
		</author>
		<imprint>
			<date type="published" when="2011" />
		</imprint>
	</monogr>
</biblStruct>

<biblStruct   xml:id="b38">
	<analytic>
		<title level="a" type="main">Heimat geht durch den Magen Oder: Das Maultaschensyndrom – Soul food in der Moderne</title>
		<author>
			<persName>
				<forename type="first">Konrad</forename>
				<surname>Köstlin</surname>
			</persName>
		</author>
	</analytic>
	<monogr>
		<title level="m">Beiträge zur Volkskünde in</title>
		<meeting><address><addrLine>Baden-Württemberg, S</addrLine></address></meeting>
		<imprint>
			<date type="published" when="1991" />
			<biblScope unit="page" from="147" to="164" />
		</imprint>
	</monogr>
</biblStruct>

<biblStruct   xml:id="b39">
	<monogr>
		<title level="m" type="main">Dalmatinska kuhinja</title>
		<author>
			<persName>
				<forename type="first">Dika</forename>
				<surname>Marjanović</surname>
			</persName>
		</author>
		<imprint>
			<date type="published" when="1984" />
			<pubPlace>Zagreb: Mladost</pubPlace>
		</imprint>
	</monogr>
</biblStruct>

<biblStruct   xml:id="b40">
	<monogr>
		<title level="m" type="main">Jugoslovenska kuhinja – specijaliteti</title>
		<author>
			<persName>
				<forename type="first">Spasenija</forename>
				<surname>Marković</surname>
			</persName>
		</author>
		<author>
			<persName>
				<surname>Pata</surname>
			</persName>
		</author>
		<imprint>
			<date type="published" when="1961" />
			<pubPlace>Beograd: Mladost</pubPlace>
		</imprint>
	</monogr>
</biblStruct>

<biblStruct   xml:id="b41">
	<monogr>
		<title/>
		<author>
			<persName>
				<forename type="first">“</forename>
				<surname>Menu „adriatic</surname>
			</persName>
		</author>
		<author>
			<persName>
				<surname>Berlin</surname>
			</persName>
		</author>
		<imprint/>
	</monogr>
</biblStruct>

<biblStruct   xml:id="b42">
	<monogr>
		<title level="m" type="main">Menu „Dalmacija grill“, Reinickendorf</title>
		<imprint/>
	</monogr>
</biblStruct>

<biblStruct   xml:id="b43">
	<monogr>
		<title/>
		<author>
			<persName>
				<forename type="first">“</forename>
				<surname>Menu „dalmacija</surname>
			</persName>
		</author>
		<author>
			<persName>
				<forename type="first">Prager</forename>
				<surname>Platz</surname>
			</persName>
		</author>
		<imprint>
			<pubPlace>Berlin</pubPlace>
		</imprint>
	</monogr>
</biblStruct>

<biblStruct   xml:id="b44">
	<analytic>
		<title level="a" type="main">Testing Food, Testing Freedom</title>
		<author>
			<persName>
				<forename type="first">Sydney</forename>
				<forename type="middle">W</forename>
				<surname>Mintz</surname>
			</persName>
		</author>
	</analytic>
	<monogr>
		<title level="m">Excursions into Eating, Power, and the Past</title>
		<meeting><address><addrLine>Boston</addrLine></address></meeting>
		<imprint>
			<publisher>Beacon Press</publisher>
			<date type="published" when="1996" />
		</imprint>
	</monogr>
</biblStruct>

<biblStruct   xml:id="b45">
	<analytic>
		<title/>
		<author>
			<persName>
				<forename type="first">Maren</forename>
				<surname>Möhring</surname>
			</persName>
		</author>
	</analytic>
	<monogr>
		<title level="m">Fremdes Essen. Die Geschichte der ausländischen Gastronomie in der Bundesrepublik Deutschland</title>
		<meeting><address><addrLine>München</addrLine></address></meeting>
		<imprint>
			<publisher>Oldenburg Verlag</publisher>
			<date type="published" when="2012" />
		</imprint>
	</monogr>
</biblStruct>

<biblStruct   xml:id="b46">
	<analytic>
		<title/>
		<author>
			<persName>
				<forename type="first">Olga</forename>
				<surname>Novak-Markovič</surname>
			</persName>
		</author>
	</analytic>
	<monogr>
		<title level="m">Jugoslavenska kuhinja</title>
		<meeting><address><addrLine>Ljubljana: Cankarjeva založba</addrLine></address></meeting>
		<imprint>
			<date type="published" when="1983" />
		</imprint>
	</monogr>
</biblStruct>

<biblStruct   xml:id="b47">
	<analytic>
		<title/>
		<author>
			<persName>
				<forename type="first">Olga</forename>
				<surname>Novak-Markovič</surname>
			</persName>
		</author>
	</analytic>
	<monogr>
		<title level="m">Die jugoslawische Küche</title>
		<meeting><address><addrLine>Ljubljana: Cankarjeva založba</addrLine></address></meeting>
		<imprint>
			<date type="published" when="1987" />
		</imprint>
	</monogr>
</biblStruct>

<biblStruct   xml:id="b48">
	<monogr>
		<title level="m" type="main">Istorija Jugoslavije. 1918-1988. Knj. 3. Socijalistička Jugoslavija</title>
		<author>
			<persName>
				<forename type="first">Branko</forename>
				<surname>Petranović</surname>
			</persName>
		</author>
		<imprint>
			<date type="published" when="1945" />
			<pubPlace>Beograd: Nolit</pubPlace>
		</imprint>
	</monogr>
</biblStruct>

<biblStruct   xml:id="b49">
	<monogr>
		<title level="m" type="main">Restaurant „Dalmacija Grill“ (Hg.): Speisekarte. Online verfügbar unter http</title>
		<imprint/>
	</monogr>
</biblStruct>

<biblStruct   xml:id="b50">
	<monogr>
		<title level="m" type="main">Das Beste der Balkanküche Innsbruck: Pinguin Verlag, S. 34.&lt;(ref&gt; &lt;ref&gt;Sundhaussen, Holm (2012): Jugoslawien und seine Nachfolgestaaten 1943-2011</title>
		<author>
			<persName>
				<forename type="first">Lotte</forename>
				<surname>Scheibenpflug</surname>
			</persName>
		</author>
		<imprint>
			<date type="published" when="1973" />
			<publisher>Böhlau</publisher>
		</imprint>
	</monogr>
	<note>Eine. ungewöhnliche Geschichte des Gewöhnlichen. Wien u.a</note>
</biblStruct>

<biblStruct   xml:id="b51">
	<monogr>
		<title level="m" type="main">Imagining the Balkans</title>
		<author>
			<persName>
				<forename type="first">Maria</forename>
				<surname>Todorova</surname>
			</persName>
		</author>
		<imprint>
			<date type="published" when="1997" />
			<publisher>Oxford University Press</publisher>
			<pubPlace>Oxford</pubPlace>
		</imprint>
	</monogr>
</biblStruct>

<biblStruct   xml:id="b52">
	<analytic>
		<title/>
		<author>
			<persName>
				<forename type="first">Vida</forename>
				<surname>Totović</surname>
			</persName>
		</author>
	</analytic>
	<monogr>
		<title level="m">Vojvođanski kuvar. Novi Sad: Forum</title>
		<imprint>
			<date type="published" when="1960" />
		</imprint>
	</monogr>
</biblStruct>

<biblStruct   xml:id="b53">
	<analytic>
		<title level="a" type="main">500 najboljih recepata burdinog kulinarskog studija: 450 fotografija u boji</title>
	</analytic>
	<monogr>
		<title level="j">Veliki Burdin kuvar</title>
		<imprint>
			<date type="published" when="1984" />
		</imprint>
	</monogr>
</biblStruct>

<biblStruct   xml:id="b54">
	<monogr>
		<title/>
		<author>
			<persName>
				<forename type="first">Mira</forename>
				<surname>Vučetić</surname>
			</persName>
		</author>
		<imprint>
			<date type="published" when="1943" />
		</imprint>
	</monogr>
</biblStruct>

<biblStruct   xml:id="b55">
	<monogr>
		<title level="m" type="main">Ethnic communities in business. Strategies for economic survival. Cambridge</title>
		<author>
			<persName>
				<forename type="first">Robin</forename>
				<forename type="middle">;</forename>
				<surname>Ward</surname>
			</persName>
		</author>
		<author>
			<persName>
				<forename type="first">Richard</forename>
				<surname>Jenkins</surname>
			</persName>
		</author>
		<imprint>
			<date type="published" when="2010" />
			<publisher>Cambridge University Press</publisher>
			<pubPlace>New York</pubPlace>
		</imprint>
	</monogr>
	<note>Comparative. ethnic and race relations series</note>
</biblStruct>

<biblStruct   xml:id="b56">
	<analytic>
		<title level="a" type="main">Kulinarstvo – dio kulture življenja i duhovne baštine u hrvatskoj turističkoj ponudi</title>
		<author>
			<persName>
				<forename type="first">Ana</forename>
				<surname>Žaper</surname>
			</persName>
		</author>
	</analytic>
	<monogr>
		<title level="m">Naše more 51</title>
		<imprint>
			<date type="published" when="2004" />
			<biblScope unit="page" from="228" to="238" />
		</imprint>
	</monogr>
</biblStruct>

