<?xml version="1.0" ?>
<tei>
	<teiHeader>
		<fileDesc xml:id="0"/>
	</teiHeader>
	<text xml:lang="en">
			<body>Nummer 9 <lb/>2008 <lb/>4,-Euro <lb/>ISSN 1862-3611 <lb/>www.giga-hamburg.de/giga-focus <lb/>Entwicklung ohne ausländische <lb/>Direktinvestitionen? Perspektiven <lb/>der arabischen Mittelmeerländer <lb/>Juliane Brach <lb/>Im Gegensatz zu anderen Entwicklungsregionen profitiert der Nahe Osten nur sehr margi­ <lb/>nal vom rasanten Anstieg des weltweiten Volumens ausländischer Direktinvestitionen (fo­ <lb/>reign direct investments – FDI). Ein wichtiges Ziel der europäischen Mittlermeerpolitik seit <lb/>Mitte der 1990er Jahre ist daher, FDI zu steigern. Im Vorfeld des EU-Gipfeltreffens im No­ <lb/>vember 2008, auf dem die Einzelheiten der Mittelmeerunion beschlossen werden sollen, <lb/>muss festgestellt werden, dass sich die Entwicklungsprobleme der Region nicht durch Stei­ <lb/>gerung der FDI lösen lassen. <lb/>Analyse: <lb/>Lediglich 5 Prozent der weltweiten FDI werden in der arabischen Welt investiert. Dar­ <lb/>an konnten weder eine Fülle nationaler wirtschaftspolitischer Maßnahmen noch inter­ <lb/>nationale Strukturanpassungsprogramme etwas ändern. <lb/>Trotz unbefriedigender Ergebnisse und einer sehr kritischen wissenschaftlichen Aus­ <lb/>einandersetzung mit den Auswirkungen ausländischer Direktinvestitionen auf die <lb/>wirtschaftliche Entwicklung von Entwicklungsländern orientieren sich nationale und <lb/>internationale Entscheidungsträger weiterhin einseitig an deren möglichen positiven <lb/>Effekten. <lb/>Nicht die geringen FDI-Zuflüsse an sich, sondern das bislang grundsätzliche Ausblei­ <lb/>ben positiver Impulse für den Ausbau international wettbewerbsfähiger Strukturen bil­ <lb/>den ein ernstzunehmendes Problem für die Perspektiven wirtschaftlicher Entwicklung <lb/>in Nahost. <lb/>Vor diesem Hintergrund wäre es im Zusammenhang mit der Formulierung der EU-<lb/>Mittelmeerunion ein wichtiges und zukunftsweisendes Signal, sich von der bisherigen <lb/>Zielsetzung – einer deutlichen Ausweitung ausländischer Direktinvestitionen – abzu­ <lb/>kehren, die den Wirtschafts-und Finanzkooperationen im Rahmen der EU-Mittelmeer­ <lb/>politik und der EU-Nachbarschaftspolitik zu Grunde liegt. <lb/>Eine erfolgreiche EU-Mittelmeerpolitik sollte in Zukunft darauf ausgerichtet sein, zen­ <lb/>trale Entwicklungshemmnisse zu beheben und durch Integration in internationale <lb/>Wertschöpfungsketten, Erfüllung technischer Normen und Erhöhung der Produktqua­ <lb/>lität die Entwicklungsperspektiven der Region zu verbessern. <lb/>Schlagwörter: Ausländische Direktinvestitionen, Wertschöpfungsketten, wirtschaftliche <lb/>Entwicklung, arabische Länder, EU-Mittelmeerpolitik <lb/> <lb/> <lb/> <lb/> <lb/> <lb/>--<lb/>GIGA Focus Nahost 9/008 <lb/>1. Einleitung <lb/>Weltweit sind ausländische Direktinvestitionen <lb/>(FDI) in den vergangenen zwanzig Jahren rapide <lb/>angestiegen. Während nach wie vor der Großteil <lb/>innerhalb der industrialisierten Länder investiert <lb/>wird, spielen FDI inzwischen auch in Entwick­ <lb/>lungsländern eine wichtige Rolle. Durch konstant <lb/>hohe Wachstumsraten, die nur vom gegenwär­ <lb/>tigen Rekordanstieg des Erdölpreises übertroffen <lb/>werden, haben sich FDI-Nettozuflüsse in Entwick­ <lb/>lungsländer von gut 25 Mrd. US$ im Jahr 1990 auf <lb/>375 Mrd. im Jahr 2006 beinahe verfünfzehnfacht. <lb/>Während Entwicklungsländer traditionell insbe­ <lb/>sondere von offiziellen Entwicklungshilfetransfers <lb/>und Rücküberweisungen von Gastarbeitern und <lb/>Emigranten an ihre Familien (Remittances) profi­ <lb/>tierten, haben FDI diese seit Anfang der 1990er im <lb/>Volumen um ein Vielfaches übertroffen und sich <lb/>als eine sehr wichtige Quelle externer Finanzströ­ <lb/>me etabliert (vgl. Abbildung 1). <lb/>Der gesamte Nahe Osten und insbesondere die <lb/>arabischen Mittelmeerländer profitieren jedoch <lb/>unterdurchschnittlich von dieser relativ neuen <lb/>Finanzierungsquelle. Nur gut 5 Prozent der welt­ <lb/>weiten FDI werden in der arabischen Welt inves­ <lb/>tiert (vgl. Brach 2007). Zudem leisten FDI zum re­ <lb/>gionalen Bruttosozialprodukt (BSP) einen Betrag <lb/>von lediglich rund 3 Prozent (siehe Abbildung 2). <lb/>0 <lb/>100 <lb/>200 <lb/>300 <lb/>400 <lb/>500 <lb/>1 9 9 0 <lb/>1 9 9 1 <lb/>1 9 9 2 <lb/>1 9 9 3 <lb/>1 9 9 4 <lb/>1 9 9 5 <lb/>1 9 9 6 <lb/>1 9 9 7 <lb/>1 9 9 8 <lb/>1 9 9 9 <lb/>2 0 0 0 <lb/>2 0 0 1 <lb/>2 0 0 2 <lb/>2 0 0 3 <lb/>2 0 0 4 <lb/>2 0 0 5 <lb/>2 0 0 6 <lb/>2 0 0 7 <lb/>$ <lb/>Remittances <lb/>ADI <lb/>Entwicklungs-<lb/>hilfe <lb/>Erdöl-<lb/>einnahmen <lb/>FDI <lb/>Abbildung 1: Kapitalzuflüsse in Entwicklungsländer (in Mrd. US$) <lb/>Quellen: Global Economic Prospects 2008 (World Bank); World Development Indicators 2008; Global Development <lb/>Finance 2008. <lb/>Wie verteilen sich die FDI innerhalb der Regi­ <lb/>on? Ist das Fehlen substanzieller FDI für die Ent­ <lb/>wicklungsperspektiven der arabischen Länder <lb/>nachteilig? Welche Konsequenzen ergeben sich für <lb/>nationale und internationale Politikmaßnahmen <lb/>und für die Politikgestaltung der Europäischen <lb/>Union? Diese Fragen sollen in diesem Beitrag nä­ <lb/>her beleuchtet werden. <lb/>2. Ausländische Direktinvestitionen in Nahost <lb/>Im Unterschied zum weltweit bereits in den 1990er <lb/>Jahren einsetzenden FDI-Anstieg hat der Nahe Os­ <lb/>ten erst in den vergangenen fünf Jahren einen An­ <lb/>stieg von FDI-Zuflüssen zu verzeichnen. Im Jahre <lb/>2006 überstiegen die FDI erstmals 50 Mrd. US$. Nach <lb/>wie vor konzentrieren sich ausländische Investo­ <lb/>ren in erster Linie auf den Energiesektor und auf <lb/>die Petrochemie im Allgemeinen. Darüber hinaus <lb/>dominieren Investitionen in Immobilien und den <lb/>Tourismus sowie in die Telekommunikationsinfra­ <lb/>struktur und den Bankensektor. Laut Schätzungen <lb/>der Weltbank und des Euro-Mediterranen Netz­ <lb/>werks zur Investitionsförderung handelt es sich <lb/>vor allem um projektgebundene Investitionen, <lb/>nicht jedoch um langfristiges Engagement der In­ <lb/>vestoren. Durch die Fokussierung auf den Erdöl­ <lb/>und Energiesektor konzentrieren sich die FDI auf <lb/>--<lb/>GIGA Focus Nahost 9/008 <lb/>die ressourcenreichen Golfmonarchien und gerade <lb/>nicht auf die ressourcenarmen arabischen Mittel­ <lb/>meerländer: Etwa die Hälfte der FDI, die 2006 in <lb/>die Region flossen (rund 25 Mrd. US$), wurden <lb/>allein in den drei Golfländern Saudi-Arabien, Ver­ <lb/>einigte Arabische Emirate und Bahrain investiert. <lb/>Von den arabischen Staaten, die kein Erdöl expor­ <lb/>tieren, profitierte Ägypten mit 10 Mrd. US$ am <lb/>meisten, gefolgt von Tunesien, Jordanien, Libanon <lb/>(jeweils ca. 3 Mrd. US$) und Marokko (2,3 Mrd. <lb/>US$). Im Unterschied dazu belaufen sich die FDI <lb/>in Syrien auf lediglich 0,6 Mrd. US$. <lb/>Abbildung 2 verdeutlicht die verhältnismäßig <lb/>geringe Bedeutung von FDI-Zuflüssen in Nahost. <lb/>FDI trugen erstmals 2006 einen größeren Anteil als <lb/>Remittances zum regionalen BSP bei. Gleichzeitig <lb/>wird aus Abbildung 2 auch die Bedeutung des Ex­ <lb/>portes von Erdöl deutlich. Da die arabischen Län­ <lb/>der sehr unterschiedlich mit der begehrten Res­ <lb/>source ausgestattet sind, kommt der Anstieg des <lb/>Erdölpreises direkt zunächst nur den ressourcen­ <lb/>reichen Ländern zugute. Darüber hinaus bleibt bei <lb/>der Betrachtung des regionalen Durchschnitts auch <lb/>die beträchtliche Heterogenität der Länder der Re­ <lb/>gion z. B. in Bezug auf die Bevölkerungsgröße und <lb/>die Arbeitsmarktsituation unberücksichtigt. <lb/>Je nach Faktorausstattung gestalten sich die <lb/>Konsequenzen und Entwicklungsherausforderun-<lb/>gen für die Länder der jeweiligen Gruppe sehr un­ <lb/>terschiedlich. Tabelle 1 orientiert sich an der Klas­ <lb/>sifizierung der arabischen Länder anhand dieser <lb/>Gesichtspunkte und fasst eine Einteilung in drei <lb/>Gruppen zusammen. <lb/>Tabelle 1: Klassifizierung der Länder nach <lb/>Faktorausstattung <lb/>Ressourcen <lb/>(Erdöl) <lb/>Arm <lb/>Reich <lb/>Arbeit <lb/>importierend <lb/>Gruppe 2: <lb/>Bahrain, Katar, <lb/>Kuwait, Oman, <lb/>Saudi-Arabien, VAE <lb/>Arbeit <lb/>exportierend <lb/>Gruppe 1: <lb/>Ägypten, Jordanien, <lb/>Libanon, Marokko, <lb/>Tunesien <lb/>Gruppe 3: <lb/>Algerien, Libyen, <lb/>Syrien <lb/>Quelle: Darstellung der Verfasserin. <lb/>Gruppe 1: Die arabischen Mittelmeerländer (Ägyp­ <lb/>ten, Jordanien, Libanon, Marokko, Tunesien) ver­ <lb/>fügen über keine oder nur sehr geringe Erdölres­ <lb/>sourcen. Diese decken zwar den Eigenverbrauch, <lb/>werden aber nicht exportiert. Trotz unterschied­ <lb/>licher Marktgröße ist die Arbeitsmarktsituation in <lb/>diesen Ländern äußerst angespannt. Moderaten <lb/>Schätzungen zufolge liegt die Arbeitslosigkeit im <lb/>Schnitt bei deutlich über 15 Prozent, die Jugend­ <lb/>arbeitslosigkeit sogar bei über 25 Prozent. Gastar­ <lb/>beiter und Emigrantenzahlungen (2007: 24,7 Mrd. <lb/></body>

			<note place="footnote">Entwicklungshilfe <lb/>FDI <lb/>Remittances <lb/>Erdöleinnahmen <lb/>30 <lb/>25 <lb/>20 <lb/>15 <lb/>10 <lb/>5 <lb/>0 <lb/>2003 <lb/>1997 <lb/>1998 <lb/>1999 <lb/>2000 <lb/>2001 <lb/>2002 <lb/>2004 <lb/>2005 <lb/>2006 <lb/>Abbildung 2: Kapitalzuflüsse in die arabischen Länder (in % des regionalen BSP <lb/>Quellen: Global Economic Prospects 2008 (World Bank); World Development Indicators 2008; Global Development <lb/>Finance 2008. <lb/></note>

			<body>--<lb/>GIGA Focus Nahost 9/008 <lb/>US$) spielen in diesen Ländern eine weitaus wich­ <lb/>tigere Rolle als FDI. Weit über dem regionalen <lb/>Durchschnitt (4 Prozent) liegend, betragen Remit-<lb/>tances z. B. in Jordanien fast 20 Prozent des BSP. <lb/>Gruppe 2: Die ressourcenreichen Golfstaaten sind <lb/>dank hoher Ölpreise inzwischen zu FDI-Nettoex­ <lb/>porteuren avanciert und investieren ihr Kapital <lb/>weltweit. Trotz fehlender umfassender Daten zu <lb/>intraregionalen FDI-Flüssen, lassen Schätzungen <lb/>der Weltbank darauf schließen, dass mindestens <lb/>9,4 Mrd. US$ der in die arabischen Mittelmeerlän­ <lb/>der (Gruppe 1) geflossenen FDI aus den Golfstaa­ <lb/>ten stammen. Über weitere wichtige Kanäle wie <lb/>Remittances und externe Kulturpolitik (etwa der <lb/>Bau von Moscheen und Kulturzentren) findet über <lb/>FDI hinaus eine Umverteilung und umfassende <lb/>Teilhabe aller arabischen Länder am Ölreichtum <lb/>der Golfstaaten statt. Um ihren Bedarf an Arbei­ <lb/>tern und Angestellten zu decken, sind in den Län­ <lb/>dern der Gruppe 2 mehrere Millionen Ausländer <lb/>beschäftigt. <lb/>Gruppe 3: Die drei Länder Algerien, Libyen und <lb/>Syrien bilden eine eigene Gruppe. Trotz ihres <lb/>Ressourcenreichtums und der Beschäftigung von <lb/>Gastarbeitern und Emigranten im Erdölsektor, <lb/>sind diese Nettoexporteure von Arbeitskräften. <lb/>FDI fließen hier ausschließlich in den Energie­ <lb/>sektor. Aufgrund der wenig diversifizierten Wirt­ <lb/>schaft bei gleichzeitig immer schnellerem Ausver­ <lb/>kauf der eigenen Ressourcen bleibt Syrien trotz <lb/>hoher Ölpreise am stärksten dem Entwicklungs­ <lb/>druck ausgesetzt. <lb/>Während in den Entwicklungsregionen Latein­ <lb/>amerika und Asien massiv und international in­ <lb/>vestiert wird, geht der Trend steigender FDI weit­ <lb/>gehend an den arabischen Ländern vorbei. Trotz <lb/>eines offensichtlichen Anwachsens bleibt das regi-<lb/>onale Niveau im internationalen Vergleich nied­ <lb/>rig. Betrachtet man nur erdölunabhängige FDI, so <lb/>wird der Anteil nahezu verschwindend gering. <lb/>3. FDI: Praxis und Theorie <lb/>Um die wirtschaftliche Entwicklung der Entwick­ <lb/>lungsländer zu fördern, hat sich die nationale und <lb/>internationale Politik in den vergangenen Jahren <lb/>vor allem an den potenziellen positiven Auswir­ <lb/>kungen ausländischer Direktinvestitionen orien­ <lb/>tiert. Vor allem drei Effekte stehen immer wieder <lb/>im Mittelpunkt entwicklungsorientierter Debatten: <lb/>FDI werden im Wettbewerb vergeben. Länder, <lb/>Volkswirtschaften, Unternehmen und Projekte <lb/>konkurrieren um die Gunst williger – in der <lb/>Regel privater – Investoren, die unter den Ge­ <lb/>sichtspunkten Produktivität und Wirtschaftlich­ <lb/>keit entscheiden. Anders als offizielle Entwick­ <lb/>lungshilfetransfers oder ­leistungen orientieren <lb/>sich FDI nicht an der Bedürftigkeit, sondern an <lb/>den Fähigkeiten eines Landes. Da FDI anders <lb/>als offizielle Entwicklungshilfetransfers oder <lb/>die Einnahmen durch den Verkauf natürlicher <lb/>Ressourcen nicht dem Staat, sondern individu­ <lb/>ellen Unternehmen und Unternehmern zuflie­ <lb/>ßen, wird dies zusätzlich positiv bewertet: Die­ <lb/>se Gelder stehen den Regimen nicht für Koopta­ <lb/>tions­ und Kompensationsleistungen zur Verfü­ <lb/>gung. Man geht deshalb davon aus, dass durch <lb/>FDI – anders als durch leistungsunabhängige <lb/>Einkommen (Renten) oder Transferzahlungen – <lb/>ein positiver Kreislauf aus Leistungsanreizen, <lb/>unternehmerischer Kreativität und Produkti­ <lb/>onssteigerung in Gang gesetzt wird. <lb/>Kapitalakkumulation bildet einen wichtigen <lb/>Faktor für Wachstum und Entwicklung. Als zu­ <lb/>sätzliche Kapitalquelle tragen FDI-Zuflüsse da-<lb/>zu bei, diesen Prozess zu beschleunigen und zu <lb/>verstetigen. <lb/>FDI gelten neben dem internationalen Handel <lb/>als wichtigster Kanal für den Technologietrans­ <lb/>fer, der sowohl direkt und beabsichtigt (z. B. <lb/>beim Transfer von Produktionstechnologien <lb/>seitens multinationaler Unternehmen) als auch <lb/>über externe und unbeabsichtigte Effekte (spill-<lb/>overs) stattfindet. <lb/>Allerdings ist diese einseitig positive Darstellung <lb/>der Auswirkungen von FDI auf Entwicklungsöko­ <lb/>nomien verkürzt und im Hinblick auf die wissen­ <lb/>schaftliche Auseinandersetzung mit FDI im Kon­ <lb/>text von Entwicklungsländern veraltet. Eine solche <lb/>Argumentation entspricht die dem Wissensstand <lb/>der 1990er Jahre. Daher ist es dringend geboten, <lb/>die Formulierung entsprechender Politikmaßnah­ <lb/>men kritisch zu reflektieren und sich den aktuellen <lb/>Stand der Forschung zunutze zu machen. <lb/>Im Gegensatz zur allgemeinen Praxis wird in <lb/>der Wissenschaft der Zusammenspiel von FDI, <lb/>wirtschaftlichem Wachstum und Entwicklung – <lb/>nach einer anfänglichen Phase der Euphorie zu <lb/>1) <lb/>2) <lb/>3) <lb/>--<lb/>GIGA Focus Nahost 9/008 <lb/>Beginn der 1990er Jahre – bis heute sehr kontro­ <lb/>vers diskutiert. Inzwischen hat sich eine umfas­ <lb/>sende Forschung etabliert, die sich diesen Zusam­ <lb/>menhängen und insbesondere den notwendigen <lb/>und hinreichenden Bedingungen widmet, unter <lb/>denen FDI zu Wachstum und Entwicklung führen <lb/>können (Helpman et al. 2004; Yeaple 2003). <lb/>Dabei werden die oben genannten Vorteile <lb/>relativiert und in Frage gestellt. FDI wirken vor <lb/>allem dann produktivitätssteigernd und als Ka­ <lb/>talysator für internationale Wettbewerbsfähigkeit <lb/>und wirtschaftlichen Aufschwung, wenn die natio-<lb/>nalen Regierungen in Infrastruktur, Bildung etc. <lb/>investieren. Eine weitere Bedingung ist, dass FDI <lb/>nicht nationale Investoren durch internationale er­ <lb/>setzen dürfen, sondern, im Gegenteil, diese ver­ <lb/>vollständigen. Auch der Verkauf nationaler Werte <lb/>(wie durch die Privatisierung von Gebäuden oder <lb/>Grundstücken), dessen Erlöse für Konsumzwecke <lb/>oder das Stopfen von Haushaltslöchern verwen­ <lb/>det und nicht reinvestiert werden, wirkt sich we­ <lb/>der im Sinne der Kapitalakkumulation noch der <lb/>Produktivitätssteigerung oder der Wettbewerbs­ <lb/>fähigkeit positiv auf die wirtschaftliche Entwick­ <lb/>lung aus. <lb/>Neueste Studien bezweifeln den positiven Zu­ <lb/>sammenhang zwischen FDI-Zuflüssen und Wachs­ <lb/>tum und Entwicklung sogar grundsätzlich und <lb/>weisen darauf hin, dass sich tatsächlich überhaupt <lb/>keine, also weder positive noch negative, Effekte <lb/>nachweisen lassen (Görg/Greenaway 2004; Herzer <lb/>et al. 2008). <lb/>Bei genauerer Betrachtung wird offensichtlich, <lb/>dass FDI in Nahost den förderlichen Kriterien <lb/>durchweg nicht gerecht werden: Auf den rasanten <lb/>Anstieg der FDI haben die nationalen Entschei­ <lb/>dungsträger mit einer Fülle wirtschaftspolitischer <lb/>Maßnahmen reagiert, die ausländische Investoren <lb/>angezogen haben: großzügige Subventionen und <lb/>Steuererleichterungen (bis hin zur Einrichtung re­ <lb/>gelrechter &quot; Steuerparadiese &quot; ), Privatisierung ren­ <lb/>tabler Sparten staatlicher Unternehmen oder Ver­ <lb/>kauf erstklassiger Grundstücke. Nach wie vor kann <lb/>keine Rede davon sein, dass nachhaltige Stand­ <lb/>ortvorteile geschaffen wurden, wie verbesserte <lb/>Infrastruktur und Ausbildung der Arbeitnehmer, <lb/>erhöhte technische Expertise, entbürokratisierte <lb/>wirtschaftliche Strukturen oder produktivitätsför­ <lb/>dernde politökonomische Strukturen (z. B. indem <lb/>wirtschaftliche Ineffizienzen schrittweise beseitigt <lb/>werden, die in der starken Renten-und geringen <lb/>Profitorientierung begründet sind). <lb/>Auch internationale Strukturanpassungspro­ <lb/>gramme werden seit mehr als einem Jahrzehnt <lb/>darauf ausgerichtet, das Geschäftsklima (business <lb/>environment) zu verbessern und setzen sich zum <lb/>Ziel, die Attraktivität der Entwicklungsländer für <lb/>FDI explizit zu erhöhen. Trotz unterschiedlicher <lb/>Schwerpunkte galt dies gleichermaßen für die Po­ <lb/>litiken der EU (EU-Mittelmeerpartnerschaft, Nach-<lb/>barschaftspolitik, Euro-Mediterrane Freihandels­ <lb/>zone) sowie die Nahostpolitik der USA (Broader <lb/>Middle East and North Africa Initiative, qualified in-<lb/>dustrial zones) und die der Weltbankgruppe. <lb/>Mit Hinblick auf die Entwicklung der FDI­Zu­ <lb/>flüsse in den Nahen Osten muss man also fest­ <lb/>stellen, dass nationale und internationale Bemü­ <lb/>hungen bisher weder zu einem substanziellen An­ <lb/>stieg noch zu einer qualitativen Verbesserung der <lb/>FDI geführt haben. Letzteres wiegt dabei ungleich <lb/>schwerer als das im internationalen Vergleich <lb/>geringe Volumen der FDI an sich. FDI haben im <lb/>Nahen Osten nicht dazu beigetragen, Quellen für <lb/>nachhaltiges wirtschaftliches Wachstum zu er­ <lb/>schließen, die als Grundlage für zukünftige wirt­ <lb/>schaftliche Entwicklung dienen können. <lb/>In der Wirtschaftstheorie werden zwei wesent­ <lb/>liche Quellen und Arten wirtschaftlichen Wachs­ <lb/>tums unterschieden: Auf der einen Seite wird ein <lb/>Wachstum als &quot; intensiv &quot; bezeichnet, das sich auf <lb/>die Ausstattung einer Volkswirtschaft mit den Pro­ <lb/>duktionsfaktoren Arbeit, Kapital und natürlichen <lb/>Ressourcen gründet, wobei die zeitliche Verän­ <lb/>derung, d. h. die Faktorakkumulation, berück­ <lb/>sichtigt wird. Hohe Wachstumsraten sind zwar <lb/>kurzfristig realisierbar, z. B. über den Verkauf <lb/>von Rohstoffen, aber sie sind schnelllebig und un­ <lb/>terliegen mittel-und langfristig starken Schwan­ <lb/>kungen. Auf der anderen Seite führen Niveau und <lb/>Geschwindigkeit des technologischen Fortschritts, <lb/>d. h. die technologischen und innovativen Kapa­ <lb/>zitäten einer Volkswirtschaft, mittelfristig zu sta­ <lb/>bilem und langfristig zu höherem wirtschaftlichen <lb/>Wachstum. Dieses auch als &quot; extensiv &quot; bezeichnete <lb/>Wachstum ist allerdings nur mittel-bis langfristig <lb/>zu erzielen und erfordert im Vergleich zu inten­ <lb/>sivem Wachstum kurz-und mittelfristig ein konti­ <lb/>nuierliches Maß an Investitionen. <lb/>Die Aufschlüsselung des Wirtschaftswachs­ <lb/>tums, das sogenannte &quot; growth accounting &quot; zeigt, <lb/>dass alle Länder des Nahen Ostens im Bezug auf <lb/>den Beitrag des technologischen Fortschritts zur <lb/>wirtschaftlichen Entwicklung unterdurchschnitt­ <lb/>liche Leistungen zeigen. Im Gegensatz zu den <lb/>--<lb/>GIGA Focus Nahost 9/008 <lb/>Entwicklungsregionen Asiens und haben die ara­ <lb/>bischen Länder durchweg negative (!) Technolo­ <lb/>giewachstumsraten. Dies bedeutet, dass fehlende <lb/>technologische Kapazitäten die Entwicklungs­ <lb/>perspektiven der Region nicht nur bremsen, son­ <lb/>dern maßgeblich konterkarieren. <lb/>Vor diesem Hintergrund wird deutlich, dass <lb/>nicht fehlende FDI an sich die Entwicklung der <lb/>Volkswirtschaften in Nahost behindern, sondern <lb/>dass vielmehr das bislang grundsätzliche Aus­ <lb/>bleiben jeglicher positiver Impulse, international <lb/>wettbewerbsfähige Strukturen aufzubauen, ein <lb/>ernstzunehmendes Problem bildet. Daraus lassen <lb/>sich folgende Konsequenzen ableiten: <lb/>Die Steigerung von FDI-Zuflüssen in die Regi­ <lb/>on ist Mittel zum Zweck, aber kein Selbstzweck, <lb/>den es um jeden Preis zu verfolgen gilt. <lb/>Ein Blick allein auf das Volumen der FDI reicht <lb/>nicht, um verlässliche Aussagen über Wettbe­ <lb/>werbsfähigkeit oder die Entwicklungsperspek­ <lb/>tiven abzuleiten. Anders als im letzten Bericht <lb/>der Weltbank (2008) dargelegt, lässt sich von <lb/>der kurzfristig positiven Entwicklung der FDI <lb/>in Nahost auf Grund von deren geringer Fä­ <lb/>higkeit, nachhaltige Wachstumsquellen zu för­ <lb/>dern, nicht auf gute Entwicklungsperspektiven <lb/>schließen. Auch Aussagen über die gesteigerte <lb/>Wettbewerbsfähigkeit des Nahen Ostens lassen <lb/>sich daraus nicht ableiten. <lb/>Mit dem im internationalen Vergleich sehr nied­ <lb/>rigen Niveau ausländischer Direktinvestitionen <lb/>lässt sich nicht rechtfertigen, dass sich interna­ <lb/>tionale Entwicklungsförderung und Struktur-<lb/>anpassungsempfehlungen auch künftig an der <lb/>Steigerung von FDI-Zuflüssen orientieren. Ein <lb/>Umdenken ist hier nicht zuletzt deshalb nötig, <lb/>weil diese Strategien der Entwicklungsförde­ <lb/>rung dazu beitragen, autoritäre Strukturen und <lb/>Regime zu erhalten und zu perpetuieren (vgl. <lb/>dazu Mattes 2008). Da in Nahost politökono­ <lb/>mische Strukturen untrennbar mit politischer <lb/>Macht und ökonomischen Renten verquickt <lb/>sind, hat auch diese bisherige Prioritäten-<lb/>setzung der EU-Mittelmeerpolitik nachhaltige <lb/>wirtschaftliche Entwicklung in Nahost eher be­ <lb/>hindert als gefördert (Brach 2008). <lb/>Während bei der Weltbank möglicherweise ein <lb/>Umdenken stattfindet (World Bank 2005), wird <lb/>sich dies für die EU-Politik erst auf dem EU-Gip­ <lb/>feltreffen im November 2008 herausstellen, wo <lb/>1) <lb/>2) <lb/>3) <lb/>die Einzelheiten der neuen gemeinsamen EU-Mit­ <lb/>telmeerpolitik &quot; Barcelona Prozess: Union für das <lb/>Mittelmeer &quot; festgelegt werden sollen (vgl. dazu <lb/>Brach 2008; Zorob 2008). Im Hinblick auf die USA <lb/>ist ein Wechsel der bisherigen Wirtschafts-und <lb/>Interessenpolitik wohl am unwahrscheinlichsten. <lb/>Es bleibt jedoch in jedem Fall die Wahl des neuen <lb/>US-Präsidenten abzuwarten, die ebenfalls im No­ <lb/>vember 2008 stattfindet. <lb/>4. Integration in Wertschöpfungsketten als <lb/>Alternative zu FDI? <lb/>Grundsätzlich werden FDI, wie bereits erwähnt, <lb/>fast immer im Vergleich zu Rohstoff-Einnahmen <lb/>und offiziellen Entwicklungshilfetransfers (Renten-<lb/>gegenüber Profitorientierung) diskutiert. Viel we­ <lb/>niger Beachtung findet indes die Möglichkeit, den <lb/>Nahen Osten in internationale und transnationale <lb/>Wertschöpfungsketten (WK) einzubinden. <lb/>Wirtschaftliche Entwicklung durch Handel <lb/>und Exportorientierung setzt voraus, dass die Ent­ <lb/>wicklungsökonomien in der Lage sind, Produkte <lb/>herzustellen, die international absetzbar sind, d. h. <lb/>den Qualitätsansprüchen und Standards interna­ <lb/>tionaler Konsumenten entsprechen. Da diese Vor­ <lb/>aussetzung jedoch häufig nicht gegeben ist, wird <lb/>regionale und intraregionale Handelsintegration <lb/>als Vorstufe und Sprungbrett zu vollständiger In-<lb/>tegration in den Weltmarkt gefördert. Dabei er­ <lb/>weist sich jedoch die gegebenenfalls geringe Kom­ <lb/>plementarität der Produktpaletten benachbarter <lb/>Entwicklungsländer als Integrationshemmnis. Der <lb/>einfachste Schritt zur Integration in die Weltmärk­ <lb/>te bleibt für Entwicklungsländer nach wie vor der <lb/>Export von Rohstoffen. Hierbei handelt es sich in <lb/>der Regel aber um einen rein extraktiven Prozess: <lb/>Die Rohstoffe werden im Land abgebaut und ge­ <lb/>fördert, während die Weiterverarbeitung und Ver­ <lb/>edelung der Produkte vorwiegend im Ausland <lb/>stattfindet. Vom wichtigen Prozess der Wertschöp­ <lb/>fung profitieren die Rohstoffexportländer wenig <lb/>oder gar nicht. <lb/>Insofern scheint es aus verschiedenen Grün­ <lb/>den eine interessante Alternative zu sein, die ara­ <lb/>bischen Mittelmeerökonomien in internationale <lb/>Wertschöpfungsketten einzubeziehen: <lb/>Anders als bei FDI behalten die lokalen Un­ <lb/>ternehmen ihre rechtliche und wirtschaftliche <lb/>Selbständigkeit. Die lokalen Unternehmer, bei <lb/>•<lb/>--<lb/>GIGA Focus Nahost 9/008 <lb/>denen es sich hauptsächlich um Zulieferer und <lb/>Lieferanten von Zwischenprodukten handelt, <lb/>gehen nicht ins Eigentum der multinationalen <lb/>Unternehmen über, sondern sind lediglich über <lb/>langfristige Verträge in diese eingebunden. <lb/>Indem die unternehmerische Selbstverantwor­ <lb/>tung und die Eigenständigkeit der Entscheidun­ <lb/>gen in Bezug auf Erfüllung, Art, Umfang, Qua­ <lb/>lität und Zuverlässigkeit der Lieferungen ge­ <lb/>wahrt bleiben, wird bei der Integration in WK <lb/>noch stärker als bei FDI der lokale Unterneh­ <lb/>mergeist (Innovativität und Wirtschaftlichkeit) <lb/>gefördert und gefordert. <lb/>Innerhalb solcher längerfristig angelegten Ko­ <lb/>operationen gibt es, im Unterschied sowohl zu <lb/>reiner Handels­ und Marktinteraktion (arms&apos;-<lb/>length-Beziehungen) als auch zur einseitigen <lb/>Zielvorgabe durch multinationale Unterneh­ <lb/>mungen (MNUs), Spielräume, um zwischen den <lb/>lokalen Unternehmen und den MNUs Ziele <lb/>zu vereinbaren. An deren Umsetzung haben <lb/>sowohl die lokalen Unternehmer als auch die <lb/>MNUs ein genuines Interesse. Selbiges gilt auch <lb/>für die Steigerung der Produktivität der lokalen <lb/>Unternehmen. <lb/>Außerdem liegen bei einer WK-Kooperation die <lb/>Eintrittsbarrieren für internationales Engage-<lb/>ment niedriger als im Falle von FDI, da die <lb/>MNUs nicht allein für deren Gelingen haften. <lb/>WK fördern damit eher kleine und mittlere Pro­ <lb/>jekte, insbesondere im verarbeitenden Gewerbe <lb/>und Dienstleistungssektor, die im Laufe der Zeit <lb/>und nach Bedarf ausgeweitet werden können. <lb/>Im Gegensatz dazu sind FDI in Entwicklungs­ <lb/>ländern meist Großprojekte im Energiesektor <lb/>oder im Zusammenhang mit Tourismus. <lb/>Schließlich gibt die Einbindung in WK lokalen <lb/>Unternehmen die Möglichkeit, aktiv und gezielt <lb/>den Technologietransfer innerhalb der Ketten zu <lb/>nutzen, um die eigenen Kapazitäten auszubau­ <lb/>en, und diesen, im Falle einer erfolgreichen lang­ <lb/>fristigen Zusammenarbeit, auch einzufordern. <lb/>Sicherlich birgt die Kooperation im Rahmen von <lb/>WK auch ähnliche Probleme wie internationales <lb/>Engagement in Entwicklungsländern durch FDI. <lb/>Es drohen z. B. die Scheinselbständigkeit lokaler <lb/>Unternehmen und deren De-facto-Abhängigkeit <lb/>von den MNUs. Gleichzeitig gilt, dass die insti­ <lb/>tutionellen Rahmenbedingungen und Kontextfak­ <lb/>toren gewährleistet sein müssen, um positive Pro­ <lb/>duktivitäts-und Wettbewerbsfähigkeiteffekte zu <lb/>•<lb/>•<lb/>•<lb/>•<lb/>realisieren. Nichtsdestoweniger bilden WK auf­ <lb/>grund ihrer besonderen Charakteristika (die De­ <lb/>zentralisierung des wirtschaftlichen Risikos, den <lb/>zu Beginn begrenzten Umfang der Kooperation <lb/>und die verbesserten Kooperationsmöglichkeiten <lb/>für kleine und mittlere lokalen Unternehmen) eine <lb/>ernstzunehmende Möglichkeit, die Wirtschaft zu <lb/>fördern und die FDI in Nahost insgesamt und <lb/>insbesondere in den ressourcenarmen arabischen <lb/>Mittlermeerländern zu vervollständigen. <lb/>Literatur <lb/></body>

			<listBibl>Brach, Juliane (2008): Economic Development in <lb/>the Arab Countries of the Middle East and North <lb/>Africa. Determinants, Constraints and Implica­ <lb/>tions for EU-Arab Relations, Dissertation, Uni­ <lb/>versität Hamburg. <lb/>Görg, H. / Greenaway, D. (2004): Much Ado About <lb/>Nothing? Do Domestic Firms Really Benefit from <lb/>Foreign Direct Investment?, in: World Bank Re­ <lb/>search Observer, Jg. 19, Nr. 2, S. 171-197. <lb/>Helpman, E. / Melitz, M. / Yeaple, S. (2003): Export <lb/>vs. FDI with Heterogenous Firms, in: American <lb/>Economic Review, Jg. 94, Nr. 1, S. 300-316. <lb/>Herzer, D. / Klasen, S. / Nowak-Lehmann, F. (2008): <lb/>In Search of FDI-led Growth in Developing <lb/>Countries: The Way Forward, in: Economic Mod-<lb/>elling, Jg. 25, S. 793-810. <lb/>World Bank (2008): Economic Development and <lb/>Prospects, Middle East and North Africa Region, <lb/>Washington D.C. <lb/>World Bank (2008): World Development Indicators, <lb/>Washington D.C. <lb/>World Bank (2005): Economic Growth in the 1990s: <lb/>Learning from a Decade of Reform, Washington <lb/>D.C. <lb/>Yeaple, S. (2003): The complex integration strat-<lb/>egies of multinationals and cross country depend <lb/>encies in the structure of foreign direct invest­ <lb/>ment, in: Journal of International Development, <lb/>Jg. 60, S. 293-314. <lb/></listBibl>

			<div type="annex">www.giga-hamburg.de/giga-focus <lb/>Das GIGA German Institute of Global and Area Studies – Leibniz-Institut für Globale und Regionale Studien <lb/>in Hamburg gibt Focus-Reihen zu Afrika, Asien, Lateinamerika und Nahost sowie zu globalen Fragen heraus, <lb/>die jeweils monatlich erscheinen. GIGA Focus Nahost wird vom GIGA Institut für Nahost-Studien redaktionell <lb/>gestaltet. Die Autoren sind für den Inhalt ihrer Beiträge verantwortlich. Das GIGA und die Autoren können für <lb/>die Richtigkeit und Vollständigkeit sowie für Konsequenzen, die sich aus der Nutzung der bereitgestellten <lb/>Informationen ergeben, nicht haftbar gemacht werden; die vertretenen Auffassungen stellen die der Autoren <lb/>und nicht unbedingt die des Instituts dar. Wurde in den Texten für Personen und Funktionen die männliche Form <lb/>gewählt, ist die weibliche Form stets mitgedacht. Download unter www.giga-hamburg.de/giga-focus. <lb/>Redaktion: Hanspeter Mattes; Gesamtverantwortlicher der Reihe: Andreas Mehler <lb/>Lektorat: Vera Rathje; Kontakt: giga-focus@giga-hamburg.de; GIGA, Neuer Jungfernstieg 21, 20354 Hamburg <lb/>Die Autorin <lb/>Dr. Juliane Brach ist Volkswirtin und wissenschaftliche Mitarbeiterin am GIGA Institut für Nahost-Studien. <lb/>E-Mail: brach@giga-hamburg.de, Webseite: http://staff.giga-hamburg.de/brach. <lb/>Gegenwärtige Forschung im GIGA zum Thema <lb/>Im Forschungsschwerpunkt 3 ( &quot; Transformation in der Globalisierung &quot; ) werden zurzeit verschiedene For­ <lb/>schungsprojekte zur wirtschaftlichen Entwicklung im Nahen und Mittleren Osten durchgeführt. Das For­ <lb/>schungsprojekt &quot; Transnationale Normbildungsnetzwerke in asymmetrischen Wirtschaftsbeziehungen (Wert­ <lb/>schöpfungsketten) &quot; von Robert Kappel und Juliane Brach befindet sich im Antragsverfahren bei der DFG. <lb/>Der GIGA-Forschungsschwerpunkt 2 ( &quot; Gewalt, Macht und Sicherheit &quot; ) beschäftigt sich u. a. mit den nega­ <lb/>tiven Folgen von Ressourcenreichtum. <lb/>GIGA-Publikationen zum Thema (Auswahl) <lb/>Ambrosius, Christian / Fritz, Barbara / Stiegler, Ursula (2008): Geldsendungen von Migranten – &quot; Manna &quot; für <lb/>die wirtschaftliche Entwicklung?, GIGA Focus Global, Nr. 10 (im Erscheinen). <lb/>Basedau, Matthias / Lacher, Wolfram (2006): A Paradox of Plenty? Rent Distribution and Political Stability in <lb/>Oil States, GIGA Working Paper, Nr. 21, April. <lb/>Beck, Martin (2007): Der Rentierstaats-Ansatz und das Problem abweichender Fälle, in: Zeitschrift für Inter­ <lb/>nationale Beziehungen, Jg. 14, Nr. 1, S. 43-70. <lb/>Brach, Juliane (2008): Constraints to Economic Growth and Development in the Middle East and North Af­ <lb/>rica, GIGA Working Paper, Nr. 85. <lb/>Brach, Juliane (2008): Economic Development in the Arab Countries of the Middle East and North Africa. De­ <lb/>terminants, Constraints and Implications for EU-Arab Relations, Dissertation, Universität Hamburg. <lb/>Brach, Juliane (2007): Die Wettbewerbsfähigkeit der arabischen Mittelmeerländer im internationalen Ver­ <lb/>gleich, GIGA Focus Nahost, Nr. 12. <lb/>Brach, Juliane (2007): Euro-Mediterranean Partnership: The Role and Impact of the Economic and Financial <lb/>Partnership, in: European Foreign Affairs Review, Jg. 12, Nr. 4, S. 555-579. <lb/>Fürtig, Henner (Hg.) (2007): The Arab Authoritarian Regime between Reform and Persistence, Newcastle. <lb/>Kappel, Robert / Brach, Juliane (2008): Handel, industrielle Cluster und internationale Netzwerke in der Globa-<lb/>lisierung: Wirtschaftswissenschaftliche Diskurse – Ein Überblick, GIGA Working Paper (im Erscheinen). <lb/>Mattes, H. (2008): &quot; We are in the Arab World, man. Forget democracy. &quot; Die schwierige Transformation auto­ <lb/>ritärer Regime in Nahost, GIGA Focus Nahost, Nr. 8. <lb/>Zorob, A. (2008): Projekt &quot; Mittelmeerunion &quot; – neuer Schub für die EU-Mittelmeerpolitik?, GIGA Focus Nah­ <lb/>ost, Nr. 5. <lb/> <lb/> <lb/> </div>


	</text>
</tei>
